setup.py
multable_czwtest/__init__.py
multable_czwtest.egg-info/PKG-INFO
multable_czwtest.egg-info/SOURCES.txt
multable_czwtest.egg-info/dependency_links.txt
multable_czwtest.egg-info/top_level.txt